[
  {
    "theme": "landing",
    "url": "http://localhost:3000/?theme=landing",
    "scores": {
      "performance": null,
      "seo": null,
      "accessibility": null,
      "bestPractices": null
    },
    "metrics": {
      "lcpMs": null,
      "inpMs": null,
      "cls": null,
      "fcpMs": null,
      "tbtMs": null,
      "speedIndexMs": null,
      "jsKb": null,
      "totalKb": null
    },
    "error": "Lighthouse failed for http://localhost:3000/?theme=landing"
  },
  {
    "theme": "typography",
    "url": "http://localhost:3000/?theme=typography",
    "scores": {
      "performance": null,
      "seo": null,
      "accessibility": null,
      "bestPractices": null
    },
    "metrics": {
      "lcpMs": null,
      "inpMs": null,
      "cls": null,
      "fcpMs": null,
      "tbtMs": null,
      "speedIndexMs": null,
      "jsKb": null,
      "totalKb": null
    },
    "error": "Lighthouse failed for http://localhost:3000/?theme=typography"
  }
]